autocontour/__init__.py
autocontour/__main__.py
autocontour/main.py
autocontour-0.0.1.dist-info/licenses/LICENSE
autocontour-0.0.1.dist-info/METADATA
autocontour-0.0.1.dist-info/WHEEL
autocontour-0.0.1.dist-info/entry_points.txt
autocontour-0.0.1.dist-info/top_level.txt
autocontour-0.0.1.dist-info/RECORD
